nexrank/__init__.py
nexrank/reranker.py
nexrank-0.1.2.dist-info/METADATA
nexrank-0.1.2.dist-info/WHEEL
nexrank-0.1.2.dist-info/RECORD
