Metadata-Version: 2.3
Name: nexrank
Version: 0.1.2
Summary: A library for state-of-the-art document reranking specifically designed for constitutional and legal documents.
Project-URL: Homepage, https://github.com/Boadzie/nexrank
Project-URL: Bug Tracker, https://github.com/Boadzie/nexrank/issues
Author-email: Daniel Boadzie <boadziedaniel43@gmail.com>
Classifier: License :: OSI Approved :: MIT License
Classifier: Operating System :: OS Independent
Classifier: Programming Language :: Python :: 3
Classifier: Topic :: Text Processing :: General
Requires-Python: >=3.11
Requires-Dist: rank-bm25>=0.2.2
Requires-Dist: scikit-learn>=1.0.2
Requires-Dist: sentence-transformers>=2.2.2
Requires-Dist: spacy>=3.5.3
Requires-Dist: torch>=2.0.1
Requires-Dist: tqdm>=4.65.0
